{
  "version": "0.2",
  "focal_node": "F",
  "metadata": {
    "created_at": "2025-10-24",
    "description": "Example ego graph for Fronx with phrase-level semantic fields"
  },
  "nodes": [
    {
      "id": "F",
      "name": "Fronx",
      "is_self": true,
      "phrases": [
        {"text": "umap dimensionality reduction", "weight": 0.9, "last_updated": "2025-10-24"},
        {"text": "audio embeddings and similarity", "weight": 0.8, "last_updated": "2025-10-24"},
        {"text": "diffusion models", "weight": 0.7, "last_updated": "2025-10-24"},
        {"text": "semantic navigation interfaces", "weight": 0.6, "last_updated": "2025-10-24"},
        {"text": "meaning representation graphs", "weight": 0.6, "last_updated": "2025-10-24"}
      ]
    },
    {
      "id": "L",
      "name": "Lara",
      "phrases": [
        {"text": "playlist flow and transitions", "weight": 0.8, "last_updated": "2025-10-20"},
        {"text": "dj set preparation", "weight": 0.7, "last_updated": "2025-10-20"},
        {"text": "embedding-based music similarity", "weight": 0.6, "last_updated": "2025-10-20"},
        {"text": "beat synchronization", "weight": 0.5, "last_updated": "2025-10-20"},
        {"text": "umap for music visualization", "weight": 0.3, "last_updated": "2025-10-20"}
      ]
    },
    {
      "id": "P",
      "name": "Pat",
      "phrases": [
        {"text": "generative audio synthesis", "weight": 0.8, "last_updated": "2025-10-22"},
        {"text": "realtime synthesis engines", "weight": 0.7, "last_updated": "2025-10-22"},
        {"text": "music technology tools", "weight": 0.7, "last_updated": "2025-10-22"},
        {"text": "embedding space exploration", "weight": 0.6, "last_updated": "2025-10-22"}
      ]
    },
    {
      "id": "K",
      "name": "Kim",
      "phrases": [
        {"text": "audio signal processing", "weight": 0.8, "last_updated": "2025-10-18"},
        {"text": "digital signal flow", "weight": 0.7, "last_updated": "2025-10-18"},
        {"text": "music machine learning", "weight": 0.6, "last_updated": "2025-10-18"},
        {"text": "semantic search for audio", "weight": 0.5, "last_updated": "2025-10-18"}
      ]
    },
    {
      "id": "S",
      "name": "Sam",
      "phrases": [
        {"text": "team cognition and collaboration", "weight": 0.8, "last_updated": "2025-10-21"},
        {"text": "organizational design patterns", "weight": 0.7, "last_updated": "2025-10-21"},
        {"text": "feedback loops in teams", "weight": 0.7, "last_updated": "2025-10-21"},
        {"text": "coordination mechanisms", "weight": 0.6, "last_updated": "2025-10-21"},
        {"text": "systems thinking approaches", "weight": 0.5, "last_updated": "2025-10-21"}
      ]
    },
    {
      "id": "T",
      "name": "Taylor",
      "phrases": [
        {"text": "cognitive systems engineering", "weight": 0.8, "last_updated": "2025-10-19"},
        {"text": "distributed cognition theory", "weight": 0.7, "last_updated": "2025-10-19"},
        {"text": "sense-making processes", "weight": 0.7, "last_updated": "2025-10-19"},
        {"text": "organizational learning", "weight": 0.6, "last_updated": "2025-10-19"}
      ]
    },
    {
      "id": "R",
      "name": "Riley",
      "phrases": [
        {"text": "coordination patterns in teams", "weight": 0.8, "last_updated": "2025-10-17"},
        {"text": "team dynamics research", "weight": 0.7, "last_updated": "2025-10-17"},
        {"text": "collective intelligence", "weight": 0.6, "last_updated": "2025-10-17"},
        {"text": "organizational behavior", "weight": 0.6, "last_updated": "2025-10-17"}
      ]
    },
    {
      "id": "B",
      "name": "Blake",
      "phrases": [
        {"text": "music cognition studies", "weight": 0.7, "last_updated": "2025-10-23"},
        {"text": "cognitive science foundations", "weight": 0.7, "last_updated": "2025-10-23"},
        {"text": "auditory perception", "weight": 0.6, "last_updated": "2025-10-23"},
        {"text": "embodied interaction design", "weight": 0.5, "last_updated": "2025-10-23"}
      ]
    }
  ],
  "edges": [
    {"source": "F", "target": "L", "actual": 0.9},
    {"source": "F", "target": "P", "actual": 0.7},
    {"source": "F", "target": "K", "actual": 0.6},
    {"source": "F", "target": "S", "actual": 0.5},
    {"source": "F", "target": "T", "actual": 0.3},
    {"source": "F", "target": "R", "actual": 0.4},
    {"source": "F", "target": "B", "actual": 0.8},
    {"source": "L", "target": "P"},
    {"source": "L", "target": "K"},
    {"source": "P", "target": "K"},
    {"source": "S", "target": "T"},
    {"source": "S", "target": "R"},
    {"source": "T", "target": "R"}
  ]
}
