{
  "F": {
    "name": "Fronx",
    "embedding": [0.25, 0.41, 0.52, 0.20, 0.10],
    "keyphrases": {
      "umap": 0.9,
      "audio embeddings": 0.8,
      "diffusion": 0.7,
      "navigation": 0.6,
      "meaning graph": 0.6
    }
  },
  "L": {
    "name": "Lara",
    "embedding": [0.22, 0.48, 0.60, 0.18, 0.12],
    "keyphrases": {
      "playlist flow": 0.8,
      "dj set": 0.7,
      "embedding": 0.6,
      "beat sync": 0.5,
      "umap": 0.3
    }
  },
  "P": {
    "name": "Pat",
    "embedding": [0.28, 0.45, 0.55, 0.22, 0.09],
    "keyphrases": {
      "generative audio": 0.8,
      "realtime synthesis": 0.7,
      "embedding space": 0.6,
      "music tech": 0.7
    }
  },
  "K": {
    "name": "Kim",
    "embedding": [0.30, 0.38, 0.48, 0.25, 0.15],
    "keyphrases": {
      "audio processing": 0.8,
      "signal flow": 0.7,
      "semantic search": 0.5,
      "music ml": 0.6
    }
  },
  "S": {
    "name": "Sam",
    "embedding": [0.64, 0.21, 0.13, 0.55, 0.42],
    "keyphrases": {
      "team cognition": 0.8,
      "feedback loop": 0.7,
      "organizational design": 0.7,
      "coordination": 0.6,
      "systems thinking": 0.5
    }
  },
  "T": {
    "name": "Taylor",
    "embedding": [0.68, 0.18, 0.10, 0.58, 0.45],
    "keyphrases": {
      "cognitive systems": 0.8,
      "sense-making": 0.7,
      "organizational learning": 0.6,
      "distributed cognition": 0.7
    }
  },
  "R": {
    "name": "Riley",
    "embedding": [0.60, 0.24, 0.16, 0.52, 0.38],
    "keyphrases": {
      "team dynamics": 0.7,
      "coordination patterns": 0.8,
      "collective intelligence": 0.6,
      "organizational behavior": 0.6
    }
  },
  "B": {
    "name": "Blake",
    "embedding": [0.45, 0.32, 0.35, 0.38, 0.28],
    "keyphrases": {
      "music cognition": 0.7,
      "auditory perception": 0.6,
      "cognitive science": 0.7,
      "embodied interaction": 0.5
    }
  },
  "edges": [
    {"u": "F", "v": "L", "actual": 0.9},
    {"u": "F", "v": "P", "actual": 0.7},
    {"u": "F", "v": "S", "actual": 0.5}
  ]
}